totallysafe/__init__.py
totallysafe-2.0.1.dist-info/METADATA
totallysafe-2.0.1.dist-info/WHEEL
totallysafe-2.0.1.dist-info/top_level.txt
totallysafe-2.0.1.dist-info/RECORD
