Metadata-Version: 2.4
Name: totallysafe
Version: 2.0.1
Summary: Totally safe package
Dynamic: summary
